cloudify_types/__init__.py
cloudify_types/utils.py
cloudify_types/component/__init__.py
cloudify_types/component/component.py
cloudify_types/component/constants.py
cloudify_types/component/operations.py
cloudify_types/component/polling.py
cloudify_types/component/utils.py
cloudify_types/shared_resource/__init__.py
cloudify_types/shared_resource/constants.py
cloudify_types/shared_resource/execute_shared_resource_workflow.py
cloudify_types/shared_resource/operations.py
cloudify_types/shared_resource/shared_resource.py
cloudify_types-5.2.3b0.dist-info/LICENSE
cloudify_types-5.2.3b0.dist-info/METADATA
cloudify_types-5.2.3b0.dist-info/WHEEL
cloudify_types-5.2.3b0.dist-info/top_level.txt
cloudify_types-5.2.3b0.dist-info/RECORD
